ibex_bluesky_core/__init__.py
ibex_bluesky_core/fitting.py
ibex_bluesky_core/log.py
ibex_bluesky_core/preprocessors.py
ibex_bluesky_core/utils.py
ibex_bluesky_core/version.py
ibex_bluesky_core/callbacks/__init__.py
ibex_bluesky_core/callbacks/_centre_of_mass.py
ibex_bluesky_core/callbacks/_document_logger.py
ibex_bluesky_core/callbacks/_file_logger.py
ibex_bluesky_core/callbacks/_fitting.py
ibex_bluesky_core/callbacks/_kafka.py
ibex_bluesky_core/callbacks/_plotting.py
ibex_bluesky_core/callbacks/_utils.py
ibex_bluesky_core/callbacks/reflectometry/__init__.py
ibex_bluesky_core/callbacks/reflectometry/_det_map.py
ibex_bluesky_core/devices/__init__.py
ibex_bluesky_core/devices/block.py
ibex_bluesky_core/devices/muon.py
ibex_bluesky_core/devices/reflectometry.py
ibex_bluesky_core/devices/dae/__init__.py
ibex_bluesky_core/devices/dae/_controls.py
ibex_bluesky_core/devices/dae/_event_mode.py
ibex_bluesky_core/devices/dae/_helpers.py
ibex_bluesky_core/devices/dae/_monitor.py
ibex_bluesky_core/devices/dae/_period.py
ibex_bluesky_core/devices/dae/_period_settings.py
ibex_bluesky_core/devices/dae/_settings.py
ibex_bluesky_core/devices/dae/_spectra.py
ibex_bluesky_core/devices/dae/_tcb_settings.py
ibex_bluesky_core/devices/polarisingdae/__init__.py
ibex_bluesky_core/devices/polarisingdae/_reducers.py
ibex_bluesky_core/devices/polarisingdae/_spectra.py
ibex_bluesky_core/devices/simpledae/__init__.py
ibex_bluesky_core/devices/simpledae/_controllers.py
ibex_bluesky_core/devices/simpledae/_reducers.py
ibex_bluesky_core/devices/simpledae/_strategies.py
ibex_bluesky_core/devices/simpledae/_waiters.py
ibex_bluesky_core/plan_stubs/__init__.py
ibex_bluesky_core/plan_stubs/_dae_table_wrapper.py
ibex_bluesky_core/plan_stubs/_num_periods_wrapper.py
ibex_bluesky_core/plan_stubs/_time_channels_wrapper.py
ibex_bluesky_core/plans/__init__.py
ibex_bluesky_core/plans/reflectometry/__init__.py
ibex_bluesky_core/plans/reflectometry/_autoalign.py
ibex_bluesky_core-1.2.0.dist-info/licenses/LICENSE
ibex_bluesky_core-1.2.0.dist-info/METADATA
ibex_bluesky_core-1.2.0.dist-info/WHEEL
ibex_bluesky_core-1.2.0.dist-info/top_level.txt
ibex_bluesky_core-1.2.0.dist-info/RECORD
