Metadata-Version: 2.4
Name: ibex-bluesky-core
Version: 1.2.0
Summary: Core bluesky plan stubs & devices for use at ISIS
Author-email: ISIS Experiment Controls <ISISExperimentControls@stfc.ac.uk>
Maintainer-email: ISIS Experiment Controls <ISISExperimentControls@stfc.ac.uk>
Project-URL: Homepage, https://github.com/isiscomputinggroup/ibex_bluesky_core
Project-URL: Bug Reports, https://github.com/isiscomputinggroup/ibex_bluesky_core/issues
Project-URL: Source, https://github.com/isiscomputinggroup/ibex_bluesky_core
Classifier: Development Status :: 3 - Alpha
Classifier: Intended Audience :: Developers
Classifier: Programming Language :: Python :: 3
Classifier: Programming Language :: Python :: 3.11
Classifier: Programming Language :: Python :: 3.12
Classifier: Programming Language :: Python :: 3.13
Classifier: Programming Language :: Python :: 3 :: Only
Requires-Python: >=3.11
License-File: LICENSE
Requires-Dist: bluesky
Requires-Dist: confluent-kafka
Requires-Dist: ophyd-async[ca]==0.14.2
Requires-Dist: lmfit
Requires-Dist: matplotlib
Requires-Dist: msgpack-numpy
Requires-Dist: numpy
Requires-Dist: orjson
Requires-Dist: scipp
Requires-Dist: scipy
Requires-Dist: scippneutron
Requires-Dist: typing-extensions
Requires-Dist: tzdata
Provides-Extra: doc
Requires-Dist: sphinx; extra == "doc"
Requires-Dist: sphinx_rtd_theme; extra == "doc"
Requires-Dist: myst_parser; extra == "doc"
Requires-Dist: sphinx-autobuild; extra == "doc"
Requires-Dist: sphinxcontrib-mermaid; extra == "doc"
Requires-Dist: sphinxcontrib-spelling; extra == "doc"
Provides-Extra: dev
Requires-Dist: ibex_bluesky_core[doc]; extra == "dev"
Requires-Dist: ruff>=0.8; extra == "dev"
Requires-Dist: pyright; extra == "dev"
Requires-Dist: pytest; extra == "dev"
Requires-Dist: pytest-asyncio; extra == "dev"
Requires-Dist: pytest-cov; extra == "dev"
Requires-Dist: pytest-env; extra == "dev"
Requires-Dist: pyqt6; extra == "dev"
Requires-Dist: uncertainties; extra == "dev"
Dynamic: license-file
